.DS_Store
AdvancedAnalytics/Forest.py
AdvancedAnalytics/Internet.py
AdvancedAnalytics/NeuralNetwork.py
AdvancedAnalytics/Regression.py
AdvancedAnalytics/ReplaceImputeEncode.py
AdvancedAnalytics/Text.py
AdvancedAnalytics/Tree.py
AdvancedAnalytics/__init__.py
AdvancedAnalytics-1.39.dist-info/.DS_Store
AdvancedAnalytics-1.39.dist-info/METADATA
AdvancedAnalytics-1.39.dist-info/WHEEL
AdvancedAnalytics-1.39.dist-info/top_level.txt
AdvancedAnalytics-1.39.dist-info/zip-safe
AdvancedAnalytics-1.39.dist-info/RECORD
