Metadata-Version: 2.1
Name: AdvancedAnalytics
Version: 1.39
Summary: Python support for 'The Art and Science of Data Analytics'
Home-page: https://github.com/tandonneur/AdvancedAnalytics
Author: Edward R Jones
Author-email: ejones@tamu.edu
Keywords: Analytics,data map,preprocessing,pre-processing,postprocessing,post-processing,NLTK,Sci-Learn,sklearn,StatsModels,web scraping,word cloud,regression,decision trees,random forest,neural network,cross validation,topic analysis,sentiment analytic,natural language processing,NLP
Classifier: Development Status :: 5 - Production/Stable
Classifier: Topic :: Utilities
Classifier: Programming Language :: Python :: 3
Classifier: License :: OSI Approved :: MIT License
Classifier: Intended Audience :: Developers
Classifier: Operating System :: OS Independent
Requires-Dist: scikit-learn
Requires-Dist: scikit-image
Requires-Dist: statsmodels
Requires-Dist: nltk
Requires-Dist: pydotplus
